__init__.py
prompts/__init__.py
prompts/prompts.py
resources/__init__.py
resources/schema.py
tools/__init__.py
tools/tools.py
utils/__init__.py
utils/frappeclient.py
utils/utils.py
erpnext_mcp_server-0.1.1.dist-info/METADATA
erpnext_mcp_server-0.1.1.dist-info/WHEEL
erpnext_mcp_server-0.1.1.dist-info/entry_points.txt
erpnext_mcp_server-0.1.1.dist-info/top_level.txt
erpnext_mcp_server-0.1.1.dist-info/RECORD
