Metadata-Version: 2.4
Name: erpnext-mcp-server
Version: 0.1.1
Summary: An MCP server for interacting with an ERPNext instance.
License-Expression: MIT
Requires-Python: >=3.10
Requires-Dist: mcp[cli]>=1.10.1
Requires-Dist: python-dotenv>=1.0.0
Requires-Dist: httpx>=0.27.0
Requires-Dist: markdownify
Requires-Dist: readabilipy
